geminiteacher/__init__.py
geminiteacher/converter.py
geminiteacher/coursemaker.py
geminiteacher/parallel.py
geminiteacher/teacher.py
geminiteacher/app/README.md
geminiteacher/app/__init__.py
geminiteacher/app/config.yaml.example
geminiteacher/app/generate_course.py
geminiteacher/gui/__init__.py
geminiteacher/gui/app.py
geminiteacher/gui/main_window.py
geminiteacher-1.0.0.dist-info/METADATA
geminiteacher-1.0.0.dist-info/WHEEL
geminiteacher-1.0.0.dist-info/entry_points.txt
geminiteacher-1.0.0.dist-info/licenses/LICENSE
geminiteacher-1.0.0.dist-info/RECORD
