Metadata-Version: 2.4
Name: geminiteacher
Version: 1.0.0
Summary: An educational content generation toolkit powered by Google's Gemini LLM
Project-URL: Homepage, https://supersheepbear.github.io/GeminiTeacher/
Project-URL: Repository, https://github.com/supersheepbear/GeminiTeacher
Project-URL: Documentation, https://supersheepbear.github.io/GeminiTeacher/
Author-email: Sheepbear <yxiong@umich.edu>
License-File: LICENSE
Keywords: ai,course,education,gemini,generator,llm
Classifier: Development Status :: 4 - Beta
Classifier: Intended Audience :: Developers
Classifier: Intended Audience :: Education
Classifier: License :: OSI Approved :: MIT License
Classifier: Programming Language :: Python
Classifier: Programming Language :: Python :: 3
Classifier: Programming Language :: Python :: 3.10
Classifier: Programming Language :: Python :: 3.11
Classifier: Programming Language :: Python :: 3.12
Classifier: Programming Language :: Python :: 3.13
Classifier: Topic :: Education
Classifier: Topic :: Software Development :: Libraries :: Python Modules
Classifier: Topic :: Text Processing
Requires-Python: <4.0,>=3.10
Requires-Dist: langchain-core>=0.1.0
Requires-Dist: langchain-google-genai>=2.1.6
Requires-Dist: langchain>=0.1.0
Requires-Dist: markitdown[all]
Requires-Dist: pydantic>=2.0.0
Requires-Dist: pyside6>=6.0
Requires-Dist: pyyaml>=6.0
